<Regions>
<Region><id>154</id><name>Bastar</name></Region>
<Region><id>155</id><name>Bilaspur</name></Region>
<Region><id>156</id><name>Dantewada</name></Region>
<Region><id>157</id><name>Dhamtari</name></Region>
<Region><id>158</id><name>Durg</name></Region>
<Region><id>159</id><name>Janjgir-Champa</name></Region>
<Region><id>160</id><name>Jashpur</name></Region>
<Region><id>161</id><name>Kanker</name></Region>
<Region><id>162</id><name>Kawardha</name></Region>
<Region><id>163</id><name>Korba</name></Region>
<Region><id>164</id><name>Koriya</name></Region>
<Region><id>165</id><name>Mahasamund</name></Region>
<Region><id>166</id><name>Raigarh</name></Region>
<Region><id>167</id><name>Raipur</name></Region>
<Region><id>168</id><name>Raj 0dgaon</name></Region>
<Region><id>169</id><name>Surguja</name></Region>
</Regions>

